DXC_AI_Test_3/ai.py
DXC_AI_Test_3-1.0.0.dist-info/LICENSE
DXC_AI_Test_3-1.0.0.dist-info/METADATA
DXC_AI_Test_3-1.0.0.dist-info/WHEEL
DXC_AI_Test_3-1.0.0.dist-info/entry_points.txt
DXC_AI_Test_3-1.0.0.dist-info/top_level.txt
DXC_AI_Test_3-1.0.0.dist-info/RECORD
