Metadata-Version: 2.1
Name: DXC-AI-Test-3
Version: 1.0.0
Summary: A Python package to add two numbers.
Home-page: UNKNOWN
Author: DXC
Author-email: pulagamnkr@gmail.com
License: MIT
Platform: UNKNOWN
Classifier: License :: OSI Approved :: MIT License
Classifier: Programming Language :: Python :: 3
Classifier: Programming Language :: Python :: 3.7
Requires-Dist: JIRA
Requires-Dist: auto-ml
Requires-Dist: Algorithmia
Requires-Dist: gitpython
Requires-Dist: flatten-json
Requires-Dist: pyjanitor
Requires-Dist: ftfy
Requires-Dist: arrow
Requires-Dist: scrubadub
Requires-Dist: yellowbrick
Requires-Dist: datacleaner
Requires-Dist: missingno
